wavspa/__init__.py
wavspa/_lorenz.py
wavspa/continuous_transform.py
wavspa/conv_fwt.py
wavspa/conv_fwt_2d.py
wavspa/conv_fwt_2d_learn.py
wavspa/conv_fwt_learn.py
wavspa/packets.py
wavspa/utils.py
wavspa/version.py
wavspa/wavelet_lifting.py
wavspa-0.0.1.dist-info/METADATA
wavspa-0.0.1.dist-info/WHEEL
wavspa-0.0.1.dist-info/top_level.txt
wavspa-0.0.1.dist-info/RECORD
