Metadata-Version: 2.1
Name: wavspa
Version: 0.0.1
Summary: Adaptive Wavelet Transform
Home-page: https://github.com/gituser/test-tackage
Author: Yufan Zhuang
Author-email: contact@gfg.com
License: MIT
Requires-Python: >=3.8
